<annotation>
	<folder>4 arreglada</folder>
	<filename>g4FlipBoth_474.jpg</filename>
	<path>C:\Users\Personal\Downloads\DMS UAO\4 arreglada\g4FlipBoth_474.jpg</path>
	<source>
		<database>Unknown</database>
	</source>
	<size>
		<width>500</width>
		<height>500</height>
		<depth>3</depth>
	</size>
	<segmented>0</segmented>
	<object>
		<name>Policecar</name>
		<pose>Unspecified</pose>
		<truncated>0</truncated>
		<difficult>0</difficult>
		<bndbox>
			<xmin>4</xmin>
			<ymin>16</ymin>
			<xmax>494</xmax>
			<ymax>393</ymax>
		</bndbox>
	</object>
</annotation>
