<annotation>
	<folder>5 Arreglada</folder>
	<filename>i8FlipHor_893.jpg</filename>
	<path>C:\Users\Personal\Downloads\DMS UAO\5 Arreglada\i8FlipHor_893.jpg</path>
	<source>
		<database>Unknown</database>
	</source>
	<size>
		<width>500</width>
		<height>500</height>
		<depth>3</depth>
	</size>
	<segmented>0</segmented>
	<object>
		<name>Policecar</name>
		<pose>Unspecified</pose>
		<truncated>0</truncated>
		<difficult>0</difficult>
		<bndbox>
			<xmin>32</xmin>
			<ymin>169</ymin>
			<xmax>464</xmax>
			<ymax>302</ymax>
		</bndbox>
	</object>
</annotation>
